{
    "1": [
        "3246517",
        "29379307"
    ],
    "2": [
        "624",
        "658"
    ],
    "3": [
        "167650499",
        "95846796"
    ],
    "4": [
        "2591",
        "1880"
    ],
    "5": [
        "7365",
        "5770"
    ],
    "6": [
        "5208",
        "1972"
    ],
    "7": [
        "3245122495150",
        "105517128211543"
    ],
    "8": [
        "344",
        "1182"
    ],
    "9": [
        "6283404590840",
        "6304576012713"
    ],
    "10": [
        "624",
        "1483"
    ],
    "11": [
        "197157",
        "234430066982597"
    ],
    "12": [
        "1546338",
        "978590"
    ],
    "13": [
        "32026",
        "89013607072065"
    ],
    "14": [
        "229980828",
        "7132"
    ],
    "15": [
        "1412971",
        "1429299"
    ],
    "16": [
        "109496",
        "551"
    ],
    "17": [
        "[2, 3, 4, 7, 5, 7, 3, 0, 7]",
        "190384609508367"
    ],
    "18": [
        "252",
        "(5+60j)"
    ],
    "19": [
        "355",
        "732978410442050"
    ],
    "20": [
        "1417",
        "1014683"
    ],
    "21": [
        "238078",
        "293919502998014"
    ],
    "22": [
        "19877757850",
        "2399"
    ],
    "23": [
        "1327",
        "df,kg,la,mp,pb,qh,sk,th,vn,ww,xp,yp,zk"
    ],
    "24": [
        "42410633905894",
        "cqm,mps,vcv,vjv,vwp,z13,z19,z25"
    ],
    "25": [
        "3057",
        "Merry Christmas!"
    ]
}